agentscope_bricks/__init__.py
agentscope_bricks/constants.py
agentscope_bricks/version.py
agentscope_bricks/adapters/__init__.py
agentscope_bricks/adapters/agentscope/__init__.py
agentscope_bricks/adapters/agentscope/tool.py
agentscope_bricks/adapters/agentscope_runtime/__init__.py
agentscope_bricks/adapters/agentscope_runtime/tool.py
agentscope_bricks/adapters/autogen/__init__.py
agentscope_bricks/adapters/autogen/tool.py
agentscope_bricks/adapters/langgraph/__init__.py
agentscope_bricks/adapters/langgraph/tool.py
agentscope_bricks/base/__base.py
agentscope_bricks/base/__init__.py
agentscope_bricks/base/component.py
agentscope_bricks/base/function_tool.py
agentscope_bricks/base/memory.py
agentscope_bricks/base/model.py
agentscope_bricks/base/prompt.py
agentscope_bricks/components/__init__.py
agentscope_bricks/components/RAGs/__init__.py
agentscope_bricks/components/RAGs/modelstudio_rag.py
agentscope_bricks/components/RAGs/modelstudio_rag_lite.py
agentscope_bricks/components/alipay/__init__.py
agentscope_bricks/components/alipay/base.py
agentscope_bricks/components/alipay/payment.py
agentscope_bricks/components/alipay/subscribe.py
agentscope_bricks/components/generations/__init__.py
agentscope_bricks/components/generations/async_image_to_video.py
agentscope_bricks/components/generations/async_speech_to_video.py
agentscope_bricks/components/generations/async_text_to_video.py
agentscope_bricks/components/generations/image_edit.py
agentscope_bricks/components/generations/image_generation.py
agentscope_bricks/components/generations/image_style_repaint.py
agentscope_bricks/components/generations/image_to_video.py
agentscope_bricks/components/generations/qwen_image_edit.py
agentscope_bricks/components/generations/qwen_image_generation.py
agentscope_bricks/components/generations/qwen_text_to_speech.py
agentscope_bricks/components/generations/speech_to_text.py
agentscope_bricks/components/generations/speech_to_video.py
agentscope_bricks-0.1.2.dist-info/METADATA
agentscope_bricks-0.1.2.dist-info/WHEEL
agentscope_bricks-0.1.2.dist-info/top_level.txt
agentscope_bricks-0.1.2.dist-info/RECORD
