Metadata-Version: 2.4
Name: agentscope-bricks
Version: 0.1.2
Summary: AgentScope-Bricks provides unified API interface for agent development
Author-email: Modelstudio Team <zhangzhicheng.zzc@alibaba-inc.com>
License-Expression: Apache-2.0
Project-URL: Homepage, https://github.com/agentscope-ai/agentscope-bricks
Project-URL: Repository, https://github.com/agentscope-ai/agentscope-bricks
Keywords: python,Agent,AIGC,LLM,Components
Classifier: Development Status :: 3 - Alpha
Classifier: Intended Audience :: Developers
Classifier: Operating System :: OS Independent
Classifier: Programming Language :: Python :: 3
Classifier: Programming Language :: Python :: 3.8
Classifier: Programming Language :: Python :: 3.9
Classifier: Programming Language :: Python :: 3.10
Classifier: Programming Language :: Python :: 3.11
Classifier: Programming Language :: Python :: 3.12
Requires-Python: >=3.10
Requires-Dist: agentscope-runtime==0.1.5b2
Requires-Dist: aiohttp
Requires-Dist: anyio
Requires-Dist: dashscope>=1.24.4
Requires-Dist: dotenv>=0.9.9
Requires-Dist: mcp>=1.14
Requires-Dist: pillow
Requires-Dist: pydantic>=2.10.6
Requires-Dist: typing_extensions
Requires-Dist: jsonref
Requires-Dist: asgiref
Requires-Dist: opentelemetry-api
Requires-Dist: opentelemetry-exporter-otlp
Requires-Dist: opentelemetry-sdk
Requires-Dist: jinja2>=3.1.6
Requires-Dist: instructor==1.7.9
Provides-Extra: dev
Requires-Dist: pytest; extra == "dev"
Requires-Dist: pytest-mock; extra == "dev"
Requires-Dist: pytest-asyncio; extra == "dev"
Requires-Dist: black; extra == "dev"
Requires-Dist: pre-commit; extra == "dev"
Provides-Extra: agentscope
Requires-Dist: agentscope>=1.0.0; extra == "agentscope"
Provides-Extra: langgraph
Requires-Dist: langgraph>=0.4.0; extra == "langgraph"
Provides-Extra: autogen
Requires-Dist: autogen-agentchat>=0.7.0; extra == "autogen"
Provides-Extra: alipay
Requires-Dist: alipay-sdk-python; extra == "alipay"
Requires-Dist: cryptography; extra == "alipay"
